setup.py
src/dcl/__init__.py
src/dcl/apps.py
src/dcl/context_processors.py
src/dcl/manage.py
src/dcl/receivers.py
src/dcl/settings.py
src/dcl/urls.py
src/dcl/wsgi.py
src/dcl/templatetags/__init__.py
src/dcl/templatetags/social_tags.py
src/django_cms_light.egg-info/PKG-INFO
src/django_cms_light.egg-info/SOURCES.txt
src/django_cms_light.egg-info/dependency_links.txt
src/django_cms_light.egg-info/entry_points.txt
src/django_cms_light.egg-info/not-zip-safe
src/django_cms_light.egg-info/requires.txt
src/django_cms_light.egg-info/top_level.txt