Metadata-Version: 1.1
Name: django-cms-light
Version: 0.0.2
Summary: Django CMS Light provides internet as a service for your friends.
Home-page: http://dcl-cms.com
Author: Django CMS Light Pic
Author-email: jpic@yourlabs.org
License: MIT
Platform: UNKNOWN
Classifier: Development Status :: 1 - Planning
Classifier: Environment :: Web Environment
Classifier: Framework :: Django
Classifier: Intended Audience :: Developers
Classifier: License :: OSI Approved :: MIT License
Classifier: Operating System :: OS Independent
Classifier: Programming Language :: Python
Classifier: Programming Language :: Python :: 2
Classifier: Topic :: Internet :: WWW/HTTP
Classifier: Topic :: Software Development :: Libraries :: Python Modules
